alat/__init__.py
alat/apps.py
alat/complexes.py
alat/crypts.py
alat/errors.py
alat/matrices.py
alat/vectors.py
alat-2.0.1.dist-info/LICENSE.txt
alat-2.0.1.dist-info/METADATA
alat-2.0.1.dist-info/WHEEL
alat-2.0.1.dist-info/top_level.txt
alat-2.0.1.dist-info/RECORD
