Metadata-Version: 2.1
Name: alat
Version: 2.0.1
Summary: Advanced Linear Algebra Toolkit
Author-email: Ahmet Can Gulmez <ahmetcangulmez02@gmail.com>
License: MIT License
Project-URL: repository, https://github.com/CanGulmez/ALAT.git
Keywords: linear algebra,matrices,vectors,math
Classifier: Development Status :: 4 - Beta
Classifier: Intended Audience :: Developers
Classifier: Operating System :: OS Independent
Classifier: License :: OSI Approved :: MIT License
Classifier: Programming Language :: Python :: 3.8
Requires-Python: >=3.8
License-File: LICENSE.txt
